gptask_cli/.gptask.example/prompts/bug-fixer.gptask
gptask_cli/.gptask.example/prompts/code-docs.gptask
gptask_cli/.gptask.example/prompts/code-helper.gptask
gptask_cli/.gptask.example/prompts/code-refactor.gptask
gptask_cli/.gptask.example/prompts/code-tester.gptask
gptask_cli/.gptask.example/prompts/doc-reviewer.gptask
gptask_cli/.gptask.example/prompts/general.gptask
gptask_cli/.gptask.example/prompts/security-auditor.gptask
gptask_cli/__init__.py
gptask_cli/conf.py
gptask_cli/git_checker.py
gptask_cli/openai_gptask.py
gptask_cli-0.2.0.dist-info/LICENSE
gptask_cli-0.2.0.dist-info/METADATA
gptask_cli-0.2.0.dist-info/WHEEL
gptask_cli-0.2.0.dist-info/entry_points.txt
gptask_cli-0.2.0.dist-info/RECORD
