Metadata-Version: 2.1
Name: gptask-cli
Version: 0.2.0
Summary: 
Author: Calum Bird
Author-email: calum@trelent.net
Requires-Python: >=3.8,<4.0
Classifier: Programming Language :: Python :: 3
Classifier: Programming Language :: Python :: 3.8
Classifier: Programming Language :: Python :: 3.9
Classifier: Programming Language :: Python :: 3.10
Classifier: Programming Language :: Python :: 3.11
Requires-Dist: click (>=8.1.6,<9.0.0)
Requires-Dist: openai (>=0.27.8,<0.28.0)
